namefile/__init__.py
namefile/core.py
namefile/version.py
namefile-0.3.1.post0.dist-info/WHEEL
namefile-0.3.1.post0.dist-info/METADATA
namefile-0.3.1.post0.dist-info/RECORD
