Metadata-Version: 2.1
Name: namefile
Version: 0.3.1.post0
Summary: generate file name from file info
Author: wangyuxin
Author-email: wangyuxin@mokahr.com
Requires-Python: >=3.8,<4.0
Classifier: Programming Language :: Python :: 3
Classifier: Programming Language :: Python :: 3.8
Classifier: Programming Language :: Python :: 3.9
Classifier: Programming Language :: Python :: 3.10
Requires-Dist: packaging (>=21.3,<22.0)
